README.md
setup.py
qb_consul/__init__.py
qb_consul.egg-info/PKG-INFO
qb_consul.egg-info/SOURCES.txt
qb_consul.egg-info/dependency_links.txt
qb_consul.egg-info/requires.txt
qb_consul.egg-info/top_level.txt