Metadata-Version: 2.1
Name: qb-consul
Version: 1.0.2
Summary: consul服务注册与获取
Home-page: http://www.qibao-tech.com
Author: Roy
Author-email: 1573277807@qq.com
License: UNKNOWN
Platform: UNKNOWN
